photoframe/__init__.py
photoframe/cli.py
photoframe/core/__init__.py
photoframe/core/exif_reader.py
photoframe/core/processor.py
photoframe/core/utils.py
photoframe/templates/__init__.py
photoframe/templates/baby.py
photoframe/templates/base.py
photoframe/templates/camera.py
photoframe/templates/date.py
photoframe-0.1.4.dist-info/METADATA
photoframe-0.1.4.dist-info/WHEEL
photoframe-0.1.4.dist-info/entry_points.txt
photoframe-0.1.4.dist-info/licenses/LICENSE
photoframe-0.1.4.dist-info/RECORD
