Metadata-Version: 2.4
Name: photoframe
Version: 0.1.4
Summary: A CLI tool for adding watermarks to photos with lossless output and Chinese font support
Project-URL: Homepage, https://github.com/aleksichen/watermarker
Project-URL: Repository, https://github.com/aleksichen/watermarker.git
Project-URL: Issues, https://github.com/aleksichen/watermarker/issues
Author-email: aleksichen <your-email@example.com>
License: MIT
License-File: LICENSE
Keywords: cli,exif,image,photo,watermark
Classifier: Development Status :: 4 - Beta
Classifier: Intended Audience :: End Users/Desktop
Classifier: License :: OSI Approved :: MIT License
Classifier: Operating System :: OS Independent
Classifier: Programming Language :: Python :: 3
Classifier: Programming Language :: Python :: 3.12
Classifier: Topic :: Multimedia :: Graphics :: Graphics Conversion
Requires-Python: >=3.12
Requires-Dist: click>=8.1.0
Requires-Dist: exifread>=3.0.0
Requires-Dist: pillow>=10.0.0
Requires-Dist: python-dateutil>=2.8.0
